{
	"paths": [
		{
			"start": { "Named": "N" },
			"end": { "Named": "NW" }
		},
		{
			"start": { "Named": "NW" },
			"end": { "Named": "S" }
		},
		{
			"start": { "Named": "N" },
			"end": { "Named": "S" }
		},
		{
			"start": { "Named": "NE" },
			"end": { "Named": "SW" },
			"is_bridge": true
		},
		{
			"start": { "Named": "NE" },
			"end": { "Named": "SE" },
			"is_bridge": true
		},
		{
			"start": { "Named": "SW" },
			"end": { "Named": "SE" },
			"is_bridge": true
		},
		{
			"start": { "Named": "NE" },
			"end": { "Named": "SW" }
		},
		{
			"start": { "Named": "NE" },
			"end": { "Named": "SE" }
		}
	]
}
